bandgraph/__init__.py
bandgraph/bandgraph.py
bandgraph-0.1.1.dist-info/METADATA
bandgraph-0.1.1.dist-info/WHEEL
bandgraph-0.1.1.dist-info/licenses/LICENSE
bandgraph-0.1.1.dist-info/RECORD
