Metadata-Version: 2.4
Name: bandgraph
Version: 0.1.1
Summary: Add your description here
License: MIT
License-File: LICENSE
Requires-Python: >=3.10
Requires-Dist: ipykernel
Requires-Dist: ipysigma
Requires-Dist: matplotlib
Requires-Dist: networkx
Requires-Dist: pandas
